convert_to_requests/__init__.py
convert_to_requests/py.typed
convert_to_requests-0.2.0.dist-info/LICENSE.GPLv3
convert_to_requests-0.2.0.dist-info/METADATA
convert_to_requests-0.2.0.dist-info/WHEEL
convert_to_requests-0.2.0.dist-info/entry_points.txt
convert_to_requests-0.2.0.dist-info/top_level.txt
convert_to_requests-0.2.0.dist-info/RECORD
